bin/debug_inputdata.py
bin/rabbit_fit.py
bin/rabbit_plot_hists.py
bin/rabbit_plot_hists_cov.py
bin/rabbit_plot_hists_uncertainties.py
bin/rabbit_plot_inputdata.py
bin/rabbit_plot_likelihood_scan.py
bin/rabbit_plot_likelihood_scan2D.py
bin/rabbit_plot_limits.py
bin/rabbit_plot_pulls_and_impacts.py
bin/rabbit_print_impacts.py
bin/rabbit_print_pulls_and_constraints.py
bin/text2hdf5.py
rabbit/__init__.py
rabbit/common.py
rabbit/datacard_converter.py
rabbit/datacard_parser.py
rabbit/debugdata.py
rabbit/fitter.py
rabbit/h5pyutils.py
rabbit/inputdata.py
rabbit/io_tools.py
rabbit/scipyhelpers.py
rabbit/tensorwriter.py
rabbit/tfhelpers.py
rabbit/workspace.py
rabbit/physicsmodels/__init__.py
rabbit/physicsmodels/angular_coefficients.py
rabbit/physicsmodels/helpers.py
rabbit/physicsmodels/physicsmodel.py
rabbit/physicsmodels/project.py
rabbit/physicsmodels/ratio.py
tests/__init__.py
tests/make_tensor.py
tests/param_model.py
tests/style_config.py
tests/symmetrizations.py
rabbit_fit-0.2.5.dist-info/METADATA
rabbit_fit-0.2.5.dist-info/WHEEL
rabbit_fit-0.2.5.dist-info/entry_points.txt
rabbit_fit-0.2.5.dist-info/top_level.txt
rabbit_fit-0.2.5.dist-info/RECORD
